iterdub/__init__.py
iterdub/iterdub.py
iterdub-0.2.0.dist-info/AUTHORS.rst
iterdub-0.2.0.dist-info/LICENSE
iterdub-0.2.0.dist-info/METADATA
iterdub-0.2.0.dist-info/WHEEL
iterdub-0.2.0.dist-info/top_level.txt
iterdub-0.2.0.dist-info/RECORD
