Metadata-Version: 2.1
Name: iterdub
Version: 0.2.0
Summary: iterdub makes generating acompact name to describe a series easy & consistent
Home-page: https://github.com/mmore500/iterdub
Author: Matthew Andres Moreno
Author-email: m.more500@gmail.com
License: MIT license
Keywords: iterdub
Platform: UNKNOWN
Classifier: Development Status :: 2 - Pre-Alpha
Classifier: Intended Audience :: Developers
Classifier: License :: OSI Approved :: MIT License
Classifier: Natural Language :: English
Classifier: Programming Language :: Python :: 3
Classifier: Programming Language :: Python :: 3.6
Classifier: Programming Language :: Python :: 3.7
Classifier: Programming Language :: Python :: 3.8
Requires-Python: >=3.6
Requires-Dist: numpy (>=1.15.0)
